Metadata-Version: 2.1
Name: clibato
Version: 1.0.1
Summary: A tool to backup/restore simple files, e.g. dot files.
Home-page: https://github.com/jigarius/clibato
Author: Jigar Mehta
Author-email: hello@jigarius.com
License: GNU LGPL v2.1
Project-URL: Documentation, https://github.com/jigarius/clibato#readme
Project-URL: Author, https://jigarius.com/
Project-URL: Tracker, https://github.com/jigarius/clibato/issues
Keywords: cli backup restore dotfile utility
Platform: UNKNOWN
Classifier: Programming Language :: Python :: 3
Classifier: License :: OSI Approved :: GNU General Public License v2 or later (GPLv2+)
Classifier: Operating System :: OS Independent
Requires-Python: >=3.6
